openlimit/__init__.py
openlimit/rate_limiters.py
openlimit/redis_rate_limiters.py
openlimit/test.py
openlimit/buckets/__init__.py
openlimit/buckets/bucket.py
openlimit/buckets/redis_bucket.py
openlimit/utilities/__init__.py
openlimit/utilities/context_decorators.py
openlimit/utilities/token_counters.py
openlimitHW-0.5.4.dist-info/LICENSE
openlimitHW-0.5.4.dist-info/METADATA
openlimitHW-0.5.4.dist-info/WHEEL
openlimitHW-0.5.4.dist-info/top_level.txt
openlimitHW-0.5.4.dist-info/RECORD
