Metadata-Version: 2.1
Name: openlimitHW
Version: 0.5.4
Summary: Rate limiter for the OpenAI API (modified by HW)
Home-page: https://github.com/williamxhero/openlimitHW
Author: williamxhero
Author-email: williamxhero <williamxhero@gmail.com>
License: MIT
Project-URL: Homepage, https://github.com/williamxhero/openlimitHW
Keywords: openai,rate-limit,limit,api,request,token,leaky-bucket,gcra,redis,asyncio
Classifier: Programming Language :: Python :: 3
Classifier: License :: OSI Approved :: MIT License
Classifier: Operating System :: OS Independent
Requires-Python: >=3
License-File: LICENSE
Requires-Dist: redis
Requires-Dist: tiktoken
